Crayfish/__init__.py
Crayfish/pool.py
Crayfish-0.0.1.dist-info/LICENSE
Crayfish-0.0.1.dist-info/METADATA
Crayfish-0.0.1.dist-info/WHEEL
Crayfish-0.0.1.dist-info/top_level.txt
Crayfish-0.0.1.dist-info/RECORD
